cubby.py
cubby-0.2.0.dist-info/METADATA
cubby-0.2.0.dist-info/WHEEL
cubby-0.2.0.dist-info/RECORD
